data_mem.v
module data_mem (
    input clk,
    input mem_write,
    input mem_read,
    input [31:0] address,
    input [31:0] write_data,
    output [31:0] read_data
);
    reg [31:0] memory [0:255];
    integer i;

    initial begin
        for (i=0; i<256; i=i+1) memory[i] = 0;
    end

    always @(posedge clk) begin
        if (mem_write) memory[address[9:2]] <= write_data;
    end

    assign read_data = (mem_read) ? memory[address[9:2]] : 32'd0;
endmodule

alu.v
module alu (
    input  [31:0] a,
    input  [31:0] b,
    input  [3:0]  alu_ctrl,
    output reg [31:0] result,
    output zero
);
    always @(*) begin
        case (alu_ctrl)
            4'b0010: result = a + b;       // ADD
            4'b0110: result = a - b;       // SUB
            4'b0000: result = a & b;       // AND
            4'b0001: result = a | b;       // OR
            4'b0111: result = (a < b) ? 32'd1 : 32'd0; // SLT
            default: result = 32'd0;
        endcase
    end
    assign zero = (result == 32'd0);
endmodule

reg_file.v
module reg_file (
    input clk,
    input reg_write_en,
    input [4:0] read_reg1,
    input [4:0] read_reg2,
    input [4:0] write_reg,
    input [31:0] write_data,
    output [31:0] read_data1,
    output [31:0] read_data2
);
    reg [31:0] registers [0:31];
    integer i;

    initial begin
        for (i = 0; i < 32; i = i + 1) registers[i] = 0;
    end

    always @(posedge clk) begin
        if (reg_write_en && write_reg != 0)
            registers[write_reg] <= write_data;
    end

    assign read_data1 = (read_reg1 == 0) ? 0 : registers[read_reg1];
    assign read_data2 = (read_reg2 == 0) ? 0 : registers[read_reg2];
endmodule

control_unit.v
module control_unit (
    input [5:0] opcode,
    input [5:0] funct,
    output reg reg_dst, branch, mem_read, mem_to_reg, 
    output reg [3:0] alu_op, 
    output reg mem_write, alu_src, reg_write
);
    always @(*) begin
        // Reset defaults
        reg_dst=0; branch=0; mem_read=0; mem_to_reg=0; 
        alu_op=0; mem_write=0; alu_src=0; reg_write=0;

        case (opcode)
            6'b000000: begin // R-Type
                reg_dst=1; reg_write=1;
                case(funct)
                    6'b100000: alu_op=4'b0010; // ADD
                    6'b100010: alu_op=4'b0110; // SUB
                    6'b100100: alu_op=4'b0000; // AND
                    6'b100101: alu_op=4'b0001; // OR
                    6'b101010: alu_op=4'b0111; // SLT
                endcase
            end
            6'b100011: begin // LW
                alu_src=1; mem_to_reg=1; reg_write=1; mem_read=1; alu_op=4'b0010;
            end
            6'b101011: begin // SW
                alu_src=1; mem_write=1; alu_op=4'b0010;
            end
            6'b000100: begin // BEQ
                branch=1; alu_op=4'b0110;
            end
            6'b001000: begin // ADDI
                alu_src=1; reg_write=1; alu_op=4'b0010;
            end
        endcase
    end
endmodule

inst_mem.v
module inst_mem (
    input [31:0] pc,
    output [31:0] instruction
);
    reg [31:0] memory [0:255];

    initial begin
        // 1. addi $1, $0, 10  (0x2001000A)
        memory[0] = 32'h2001000A;
        // 2. addi $2, $0, 20  (0x20020014)
        memory[1] = 32'h20020014;
        // 3. add $3, $1, $2   (0x00221820) -> Result should be 30
        memory[2] = 32'h00221820;
        // 4. sw $3, 4($0)     (0xAC030004) -> Write 30 to Mem Addr 4
        memory[3] = 32'hAC030004;
        // 5. lw $4, 4($0)     (0x8C040004) -> Read 30 from Mem into $4
        memory[4] = 32'h8C040004;
        // 6. beq $1, $1, -1   (0x1021FFFF) -> Infinite Loop here
        memory[5] = 32'h1021FFFF;
    end

    assign instruction = memory[pc[9:2]];
endmodule

mips_cpu.v
module mips_cpu (
    input clk,
    input reset,
    output [31:0] pc_out,
    output [31:0] alu_result
);
    reg [31:0] pc;
    wire [31:0] pc_next, pc_plus4, pc_branch, instruction, sign_ext_imm;
    wire [31:0] read_data1, read_data2, src_b, result, mem_read_data, write_back_data;
    wire [4:0]  write_reg;
    wire reg_dst, branch, mem_read, mem_to_reg, mem_write, alu_src, reg_write, zero;
    wire [3:0] alu_op;

    // PC Logic
    always @(posedge clk or posedge reset) begin
        if (reset) pc <= 0;
        else pc <= pc_next;
    end

    assign pc_plus4 = pc + 4;
    assign sign_ext_imm = {{16{instruction[15]}}, instruction[15:0]};
    assign pc_branch = pc_plus4 + (sign_ext_imm << 2);
    assign pc_next = (branch & zero) ? pc_branch : pc_plus4;

    // Instances
    inst_mem imem (.pc(pc), .instruction(instruction));

    control_unit ctrl (
        .opcode(instruction[31:26]), .funct(instruction[5:0]),
        .reg_dst(reg_dst), .branch(branch), .mem_read(mem_read),
        .mem_to_reg(mem_to_reg), .alu_op(alu_op), .mem_write(mem_write),
        .alu_src(alu_src), .reg_write(reg_write)
    );

    assign write_reg = (reg_dst) ? instruction[15:11] : instruction[20:16];

    reg_file rf (
        .clk(clk), .reg_write_en(reg_write),
        .read_reg1(instruction[25:21]), .read_reg2(instruction[20:16]),
        .write_reg(write_reg), .write_data(write_back_data),
        .read_data1(read_data1), .read_data2(read_data2)
    );

    assign src_b = (alu_src) ? sign_ext_imm : read_data2;

    alu main_alu (
        .a(read_data1), .b(src_b), .alu_ctrl(alu_op),
        .result(result), .zero(zero)
    );

    data_mem dmem (
        .clk(clk), .mem_write(mem_write), .mem_read(mem_read),
        .address(result), .write_data(read_data2), .read_data(mem_read_data)
    );

    assign write_back_data = (mem_to_reg) ? mem_read_data : result;
    
    // Debug Output
    assign pc_out = pc;
    assign alu_result = result;
endmodule

mips_cpu_tb.v
`timescale 1ns/1ns

module mips_cpu_tb;
    reg clk;
    reg reset;
    wire [31:0] pc_out;
    wire [31:0] alu_result;

    mips_cpu uut (
        .clk(clk), .reset(reset),
        .pc_out(pc_out), .alu_result(alu_result)
    );

    always #5 clk = ~clk;

    initial begin
        $dumpfile("mips_cpu_test.vcd");
        $dumpvars(0, mips_cpu_tb);
        
        clk = 0; reset = 1;
        #10;
        reset = 0;
        
        // Run long enough for the program to finish
        #200;
        $finish;
    end
endmodule

mips_cpu_test.vcd
$date
	Wed Dec 17 00:18:34 2025
$end
$version
	Icarus Verilog
$end
$timescale
	1ns
$end
$scope module mips_cpu_tb $end
$var wire 32 ! pc_out [31:0] $end
$var wire 32 " alu_result [31:0] $end
$var reg 1 # clk $end
$var reg 1 $ reset $end
$scope module uut $end
$var wire 32 % alu_result [31:0] $end
$var wire 1 # clk $end
$var wire 32 & pc_out [31:0] $end
$var wire 1 $ reset $end
$var wire 1 ' zero $end
$var wire 5 ( write_reg [4:0] $end
$var wire 32 ) write_back_data [31:0] $end
$var wire 32 * src_b [31:0] $end
$var wire 32 + sign_ext_imm [31:0] $end
$var wire 32 , result [31:0] $end
$var wire 1 - reg_write $end
$var wire 1 . reg_dst $end
$var wire 32 / read_data2 [31:0] $end
$var wire 32 0 read_data1 [31:0] $end
$var wire 32 1 pc_plus4 [31:0] $end
$var wire 32 2 pc_next [31:0] $end
$var wire 32 3 pc_branch [31:0] $end
$var wire 1 4 mem_write $end
$var wire 1 5 mem_to_reg $end
$var wire 32 6 mem_read_data [31:0] $end
$var wire 1 7 mem_read $end
$var wire 32 8 instruction [31:0] $end
$var wire 1 9 branch $end
$var wire 1 : alu_src $end
$var wire 4 ; alu_op [3:0] $end
$var reg 32 < pc [31:0] $end
$scope module ctrl $end
$var wire 6 = funct [5:0] $end
$var wire 6 > opcode [5:0] $end
$var reg 4 ? alu_op [3:0] $end
$var reg 1 : alu_src $end
$var reg 1 9 branch $end
$var reg 1 7 mem_read $end
$var reg 1 5 mem_to_reg $end
$var reg 1 4 mem_write $end
$var reg 1 . reg_dst $end
$var reg 1 - reg_write $end
$upscope $end
$scope module dmem $end
$var wire 1 # clk $end
$var wire 1 7 mem_read $end
$var wire 1 4 mem_write $end
$var wire 32 @ write_data [31:0] $end
$var wire 32 A read_data [31:0] $end
$var wire 32 B address [31:0] $end
$var integer 32 C i [31:0] $end
$upscope $end
$scope module imem $end
$var wire 32 D instruction [31:0] $end
$var wire 32 E pc [31:0] $end
$upscope $end
$scope module main_alu $end
$var wire 4 F alu_ctrl [3:0] $end
$var wire 32 G b [31:0] $end
$var wire 1 ' zero $end
$var wire 32 H a [31:0] $end
$var reg 32 I result [31:0] $end
$upscope $end
$scope module rf $end
$var wire 1 # clk $end
$var wire 5 J read_reg1 [4:0] $end
$var wire 5 K read_reg2 [4:0] $end
$var wire 1 - reg_write_en $end
$var wire 32 L write_data [31:0] $end
$var wire 5 M write_reg [4:0] $end
$var wire 32 N read_data2 [31:0] $end
$var wire 32 O read_data1 [31:0] $end
$var integer 32 P i [31:0] $end
$upscope $end
$upscope $end
$upscope $end
$enddefinitions $end
$comment Show the parameter values. $end
$dumpall
$end
#0
$dumpvars
b100000 P
b0 O
b0 N
b1 M
b1010 L
b1 K
b0 J
b1010 I
b0 H
b1010 G
b10 F
b0 E
b100000000000010000000000001010 D
b100000000 C
b1010 B
b0 A
b0 @
b10 ?
b1000 >
b1010 =
b0 <
b10 ;
1:
09
b100000000000010000000000001010 8
07
b0 6
05
04
b101100 3
b100 2
b100 1
b0 0
b0 /
0.
1-
b1010 ,
b1010 +
b1010 *
b1010 )
b1 (
0'
b0 &
b1010 %
1$
0#
b1010 "
b0 !
$end
#5
b1010 /
b1010 @
b1010 N
1#
#10
0#
0$
#15
b10100 )
b10100 L
b10100 "
b10100 %
b10100 ,
b10100 B
b10100 I
b0 /
b0 @
b0 N
b10 (
b10 M
1-
1:
b10 ;
b10 ?
b10 F
b10100 *
b10100 G
b10 K
b10100 =
b10100 +
b1000 2
b100000000000100000000000010100 8
b100000000000100000000000010100 D
b1011000 3
b1000 1
b100 !
b100 &
b100 <
b100 E
1#
#20
0#
#25
b11110 )
b11110 L
b11 (
b11 M
b11110 "
b11110 %
b11110 ,
b11110 B
b11110 I
b1010 0
b1010 H
b1010 O
1.
1-
0:
b10 ;
b10 ?
b10 F
b10100 *
b10100 G
b1 J
b100000 =
b0 >
b1100000100000 +
b10100 /
b10100 @
b10100 N
b1100 2
b1000100001100000100000 8
b1000100001100000100000 D
b110000010001100 3
b1100 1
b1000 !
b1000 &
b1000 <
b1000 E
1#
#30
0#
#35
b100 )
b100 L
b100 *
b100 G
b100 "
b100 %
b100 ,
b100 B
b100 I
b11110 /
b11110 @
b11110 N
b0 0
b0 H
b0 O
14
1:
0-
b10 ;
b10 ?
b10 F
0.
b11 K
b0 J
b100 =
b101011 >
b100 +
b10000 2
b10101100000000110000000000000100 8
b10101100000000110000000000000100 D
b100000 3
b10000 1
b1100 !
b1100 &
b1100 <
b1100 E
1#
#40
0#
#45
b11110 6
b11110 A
b11110 )
b11110 L
b0 /
b0 @
b0 N
b100 (
b100 M
17
1-
15
1:
04
b10 ;
b10 ?
b10 F
b100 K
b100011 >
b10100 2
b10001100000001000000000000000100 8
b10001100000001000000000000000100 D
b100100 3
b10100 1
b10000 !
b10000 &
b10000 <
b10000 E
1#
#50
0#
#55
1'
b0 )
b0 L
b0 6
b0 A
b0 "
b0 %
b0 ,
b0 B
b0 I
b1010 0
b1010 H
b1010 O
b1 (
b1 M
19
0-
0:
b110 ;
b110 ?
b110 F
05
07
b1010 *
b1010 G
b1 K
b1 J
b111111 =
b100 >
b11111111111111111111111111111111 +
b1010 /
b1010 @
b1010 N
b10100 2
b10000001000011111111111111111 8
b10000001000011111111111111111 D
b10100 3
b11000 1
b10100 !
b10100 &
b10100 <
b10100 E
1#
